rnm/__init__.py
rnm/collect.py
rnm/process.py
rnm-0.4.3.dist-info/WHEEL
rnm-0.4.3.dist-info/METADATA
rnm-0.4.3.dist-info/RECORD
