Metadata-Version: 2.1
Name: rnm
Version: 0.4.3
Summary: 
Author: KhalidCK
Requires-Python: >=3.8,<4.0
Classifier: Programming Language :: Python :: 3
Classifier: Programming Language :: Python :: 3.10
Classifier: Programming Language :: Python :: 3.8
Classifier: Programming Language :: Python :: 3.9
Requires-Dist: beautifulsoup4 (>=4.9.3,<5.0.0)
Requires-Dist: clean-text[gpl] (>=0.3.0,<0.4.0)
Requires-Dist: loguru (>=0.5.3,<0.6.0)
Requires-Dist: pandas (>=1.1.5,<2.0.0)
Requires-Dist: pydantic (>=1.7.3,<2.0.0)
Requires-Dist: python-slugify (>=4.0.1,<5.0.0)
Requires-Dist: requests (>=2.25.0,<3.0.0)
